[
  {
    "title": "tylenol",
    "photo_Url": "https://res.cloudinary.com/dhqsixgmo/image/upload/v1664851514/pill-git-it-images/blue-cap_tuv1qy.jpg",
    "type": "capsule",
    "color": "blue",
    "imprint": "3e4",
    "description": "oblong",
    "author_id": 1
  },
  {
    "title": "advil",
    "photo_Url": "https://res.cloudinary.com/dhqsixgmo/image/upload/v1664851514/pill-git-it-images/blue-caplt_gl2v0s.jpg",
    "type":  "caplet",
    "color": "blue",
    "imprint": "t12",
    "description": "oval",
    "author_id": 2
  },
  {
    "title": "motrin",
    "photo_Url": "https://res.cloudinary.com/dhqsixgmo/image/upload/v1664851514/pill-git-it-images/white-tab_m8srwd.jpg",
    "type": "tablet",
    "color": "white",
    "imprint": "l03",
    "description": "round",
    "author_id": 3
  },
  {
    "title": "aleve",
    "photo_Url": "https://res.cloudinary.com/dhqsixgmo/image/upload/v1664851514/pill-git-it-images/pink-oval-cap_pnb0lj.jpg",
    "type": "gelcap",
    "color": "pink",
    "imprint": "s20",
    "description": "oval",
    "author_id": 2
  },
  {
    "title": "ibuprofen",
    "photo_Url": "https://res.cloudinary.com/dhqsixgmo/image/upload/v1664851514/pill-git-it-images/yellow-cap_x9kpkf.jpg",
    "type": "capsule",
    "color": "yellow",
    "imprint": "e45",
    "description": "oblong",
    "author_id": 4
  },
  {
    "title": "aspirin",
    "photo_Url": "https://res.cloudinary.com/dhqsixgmo/image/upload/v1664851514/pill-git-it-images/white-tab_m8srwd.jpg",
    "type": "tablet",
    "color": "white",
    "imprint": "p12",
    "description": "round",
    "author_id": 2
  },    
  {
    "title": "midol",
    "photo_Url": "https://res.cloudinary.com/dhqsixgmo/image/upload/v1664851515/pill-git-it-images/rect-tab_ej3ymc.jpg",
    "type": "tablet",
    "color": "white",
    "imprint": "s07",
    "description": "rectangle",
    "author_id": 1
  }
]